README.md
setup.cfg
setup.py
SurfaceBuilder247/__init__.py
SurfaceBuilder247/gridCreate.py
SurfaceBuilder247/locationIndex.py
SurfaceBuilder247/modelRun.py
SurfaceBuilder247/projectParams.py
SurfaceBuilder247/sb247.py
SurfaceBuilder247/unit_tests.py
SurfaceBuilder247.egg-info/PKG-INFO
SurfaceBuilder247.egg-info/SOURCES.txt
SurfaceBuilder247.egg-info/dependency_links.txt
SurfaceBuilder247.egg-info/not-zip-safe
SurfaceBuilder247.egg-info/top_level.txt