Metadata-Version: 2.1
Name: SurfaceBuilder247
Version: 0.5
Summary: Surface Builder 24/7
Home-page: UNKNOWN
Author-email: geodata@soton.ac.uk
License: UNKNOWN
Platform: UNKNOWN
